kotlin version: 2.0.21
error message: org.jetbrains.kotlin.codegen.CompilationException: Back-end (JVM) Internal error: Couldn't transform method node:
findChapterHeadings (Ljava/io/File;Lcom/huangder/lumibooks/util/parser/TxtParser$EncodingInfo;)Ljava/util/List;:
    // annotable parameter count: 2 (visible)
    // annotable parameter count: 2 (invisible)
    TRYCATCHBLOCK L0 L1 L2 java/lang/Throwable
    TRYCATCHBLOCK L0 L1 L3 null
    TRYCATCHBLOCK L2 L3 L3 null
    TRYCATCHBLOCK L3 L4 L3 null
   L5
    LINENUMBER 117 L5
    GETSTATIC com/huangder/lumibooks/util/parser/TxtParser.CHAPTER_PATTERNS : Ljava/util/List;
    INVOKEINTERFACE java/util/List.iterator ()Ljava/util/Iterator; (itf)
    ASTORE 3
   L6
    INVOKESTATIC kotlin/jvm/internal/InlineMarker.beforeInlineCall ()V
   L7
    INVOKESTATIC kotlin/jvm/internal/$PseudoInsn.FAKE_ALWAYS_FALSE_IFEQ ()I
    IFEQ L8
    ALOAD 3
    INVOKEINTERFACE java/util/Iterator.hasNext ()Z (itf)
    IFEQ L8
    ALOAD 3
    INVOKEINTERFACE java/util/Iterator.next ()Ljava/lang/Object; (itf)
    CHECKCAST kotlin/text/Regex
    ASTORE 4
   L9
    LINENUMBER 118 L9
    NOP
   L10
    NEW java/util/ArrayList
    DUP
    INVOKESPECIAL java/util/ArrayList.<init> ()V
    CHECKCAST java/util/List
    NOP
    GOTO L11
   L11
    LINENUMBER 118 L11
    ASTORE 5
   L12
    LINENUMBER 119 L12
    ALOAD 0
    ASTORE 6
    ALOAD 2
    INVOKEVIRTUAL com/huangder/lumibooks/util/parser/TxtParser$EncodingInfo.getContentStart ()J
    LSTORE 7
    ALOAD 1
    INVOKEVIRTUAL java/io/File.length ()J
    LSTORE 9
    INVOKESTATIC kotlin/jvm/internal/InlineMarker.beforeInlineCall ()V
    NOP
   L13
    ICONST_0
    ISTORE 11
   L14
    LINENUMBER 534 L14
    LLOAD 9
    LLOAD 7
    LCMP
    IFGT L15
    GETSTATIC kotlin/Unit.INSTANCE : Lkotlin/Unit;
    POP
    NOP
    GOTO L16
   L15
    LINENUMBER 535 L15
    NEW java/io/RandomAccessFile
    DUP
    ALOAD 1
    LDC "r"
    INVOKESPECIAL java/io/RandomAccessFile.<init> (Ljava/io/File;Ljava/lang/String;)V
    CHECKCAST java/io/Closeable
    ASTORE 12
    ACONST_NULL
    ASTORE 13
   L17
    INVOKESTATIC kotlin/jvm/internal/$PseudoInsn.SAVE_STACK_BEFORE_TRY ()V
   L0
    NOP
    INVOKESTATIC kotlin/jvm/internal/$PseudoInsn.RESTORE_STACK_IN_TRY_CATCH ()V
    ALOAD 12
    CHECKCAST java/io/RandomAccessFile
    ASTORE 14
   L18
    ICONST_0
    ISTORE 15
   L19
    LINENUMBER 536 L19
    ALOAD 14
    LLOAD 7
    INVOKEVIRTUAL java/io/RandomAccessFile.seek (J)V
   L20
    LINENUMBER 537 L20
    LDC 65536
    NEWARRAY T_BYTE
    ASTORE 16
   L21
    LINENUMBER 538 L21
    SIPUSH 512
    NEWARRAY T_BYTE
    ASTORE 17
   L22
    LINENUMBER 539 L22
    NEW kotlin/jvm/internal/Ref$IntRef
    DUP
    INVOKESPECIAL kotlin/jvm/internal/Ref$IntRef.<init> ()V
    ASTORE 18
   L23
    LINENUMBER 540 L23
    LLOAD 7
    LSTORE 19
   L24
    LINENUMBER 541 L24
    NEW kotlin/jvm/internal/Ref$LongRef
    DUP
    INVOKESPECIAL kotlin/jvm/internal/Ref$LongRef.<init> ()V
    ASTORE 21
   L25
    ALOAD 21
    LLOAD 7
    PUTFIELD kotlin/jvm/internal/Ref$LongRef.element : J
   L26
    LINENUMBER 542 L26
    LLOAD 9
    LLOAD 7
    LSUB
    LSTORE 22
   L27
    LINENUMBER 543 L27
    ALOAD 2
    INVOKEVIRTUAL com/huangder/lumibooks/util/parser/TxtParser$EncodingInfo.getCharset ()Ljava/nio/charset/Charset;
    GETSTATIC kotlin/text/Charsets.UTF_16LE : Ljava/nio/charset/Charset;
    INVOKESTATIC kotlin/jvm/internal/Intrinsics.areEqual (Ljava/lang/Object;Ljava/lang/Object;)Z
    IFNE L28
    ALOAD 2
    INVOKEVIRTUAL com/huangder/lumibooks/util/parser/TxtParser$EncodingInfo.getCharset ()Ljava/nio/charset/Charset;
    GETSTATIC kotlin/text/Charsets.UTF_16BE : Ljava/nio/charset/Charset;
    INVOKESTATIC kotlin/jvm/internal/Intrinsics.areEqual (Ljava/lang/Object;Ljava/lang/Object;)Z
    IFEQ L29
   L28
    ICONST_1
    GOTO L30
   L29
    ICONST_0
   L30
    ISTORE 24
   L31
    LINENUMBER 551 L31
    LLOAD 22
    LCONST_0
    LCMP
    IFLE L32
   L33
    LINENUMBER 552 L33
    ALOAD 16
    ARRAYLENGTH
    I2L
    LLOAD 22
    INVOKESTATIC java/lang/Math.min (JJ)J
    GOTO L34
   L34
    LINENUMBER 552 L34
    L2I
    ISTORE 25
   L35
    LINENUMBER 553 L35
    ALOAD 14
    ALOAD 16
    ICONST_0
    ILOAD 25
    INVOKEVIRTUAL java/io/RandomAccessFile.read ([BII)I
    ISTORE 26
   L36
    LINENUMBER 554 L36
    ILOAD 26
    ICONST_0
    IF_ICMPGT L37
    GOTO L32
   L37
    LINENUMBER 556 L37
    ILOAD 24
    IFEQ L38
   L39
    LINENUMBER 557 L39
    ICONST_0
    ISTORE 27
   L40
    LINENUMBER 558 L40
    ILOAD 27
    ICONST_1
    IADD
    ILOAD 26
    IF_ICMPGE L41
   L42
    LINENUMBER 559 L42
    ALOAD 2
    INVOKEVIRTUAL com/huangder/lumibooks/util/parser/TxtParser$EncodingInfo.getCharset ()Ljava/nio/charset/Charset;
    GETSTATIC kotlin/text/Charsets.UTF_16LE : Ljava/nio/charset/Charset;
    INVOKESTATIC kotlin/jvm/internal/Intrinsics.areEqual (Ljava/lang/Object;Ljava/lang/Object;)Z
    IFEQ L43
   L44
    LINENUMBER 560 L44
    ALOAD 16
    ILOAD 27
    BALOAD
    BIPUSH 10
    IF_ICMPNE L45
    ALOAD 16
    ILOAD 27
    ICONST_1
    IADD
    BALOAD
    IFNE L45
    ICONST_1
    GOTO L46
   L45
    ICONST_0
   L46
    GOTO L47
   L43
    LINENUMBER 562 L43
    ALOAD 16
    ILOAD 27
    BALOAD
    IFNE L48
    ALOAD 16
    ILOAD 27
    ICONST_1
    IADD
    BALOAD
    BIPUSH 10
    IF_ICMPNE L48
    ICONST_1
    GOTO L47
   L48
    ICONST_0
   L47
    LINENUMBER 559 L47
    ISTORE 28
   L49
    LINENUMBER 564 L49
    ILOAD 28
    IFEQ L50
   L51
    LINENUMBER 565 L51
    ALOAD 21
    ALOAD 17
    ALOAD 18
    ALOAD 2
    LLOAD 19
    ILOAD 27
    I2L
    LADD
    ICONST_2
    I2L
    LADD
    INVOKESTATIC com/huangder/lumibooks/util/parser/TxtParser.forEachLinePrefix$lambda$17$emit$16 (Lkotlin/jvm/functions/Function3;Lkotlin/jvm/internal/Ref$LongRef;[BLkotlin/jvm/internal/Ref$IntRef;Lcom/huangder/lumibooks/util/parser/TxtParser$EncodingInfo;J)V
    GOTO L52
   L50
    LINENUMBER 566 L50
    ALOAD 18
    GETFIELD kotlin/jvm/internal/Ref$IntRef.element : I
    ICONST_2
    IADD
    ALOAD 17
    ARRAYLENGTH
    IF_ICMPGT L52
   L53
    LINENUMBER 567 L53
    ALOAD 17
    ALOAD 18
    GETFIELD kotlin/jvm/internal/Ref$IntRef.element : I
    ISTORE 29
    ALOAD 18
    ILOAD 29
    ICONST_1
    IADD
    PUTFIELD kotlin/jvm/internal/Ref$IntRef.element : I
    ILOAD 29
    ALOAD 16
    ILOAD 27
    BALOAD
    BASTORE
   L54
    LINENUMBER 568 L54
    ALOAD 17
    ALOAD 18
    GETFIELD kotlin/jvm/internal/Ref$IntRef.element : I
    ISTORE 29
    ALOAD 18
    ILOAD 29
    ICONST_1
    IADD
    PUTFIELD kotlin/jvm/internal/Ref$IntRef.element : I
    ILOAD 29
    ALOAD 16
    ILOAD 27
    ICONST_1
    IADD
    BALOAD
    BASTORE
   L52
    LINENUMBER 570 L52
    IINC 27 2
    ILOAD 27
   L55
    POP
    GOTO L40
   L41
    GOTO L56
   L38
    LINENUMBER 573 L38
    ICONST_0
    ISTORE 27
   L57
    ILOAD 27
    ILOAD 26
    IF_ICMPLT L58
    GOTO L56
   L58
    LINENUMBER 574 L58
    ALOAD 16
    ILOAD 27
    BALOAD
    BIPUSH 10
    IF_ICMPNE L59
   L60
    LINENUMBER 575 L60
    ALOAD 21
    ALOAD 17
    ALOAD 18
    ALOAD 2
    LLOAD 19
    ILOAD 27
    I2L
    LADD
    ICONST_1
    I2L
    LADD
    INVOKESTATIC com/huangder/lumibooks/util/parser/TxtParser.forEachLinePrefix$lambda$17$emit$16 (Lkotlin/jvm/functions/Function3;Lkotlin/jvm/internal/Ref$LongRef;[BLkotlin/jvm/internal/Ref$IntRef;Lcom/huangder/lumibooks/util/parser/TxtParser$EncodingInfo;J)V
    GOTO L61
   L59
    LINENUMBER 576 L59
    ALOAD 18
    GETFIELD kotlin/jvm/internal/Ref$IntRef.element : I
    ALOAD 17
    ARRAYLENGTH
    IF_ICMPGE L61
   L62
    LINENUMBER 577 L62
    ALOAD 17
    ALOAD 18
    GETFIELD kotlin/jvm/internal/Ref$IntRef.element : I
    ISTORE 28
    ALOAD 18
    ILOAD 28
    ICONST_1
    IADD
    PUTFIELD kotlin/jvm/internal/Ref$IntRef.element : I
    ILOAD 28
    ALOAD 16
    ILOAD 27
    BALOAD
    BASTORE
   L61
    LINENUMBER 573 L61
    IINC 27 1
    GOTO L57
   L56
    LINENUMBER 582 L56
    LLOAD 19
    ILOAD 26
    I2L
    LADD
    LSTORE 19
   L63
    LINENUMBER 583 L63
    LLOAD 22
    ILOAD 26
    I2L
    LSUB
    LSTORE 22
   L64
    GOTO L31
   L32
    LINENUMBER 585 L32
    ALOAD 21
    GETFIELD kotlin/jvm/internal/Ref$LongRef.element : J
    LLOAD 9
    LCMP
    IFGE L65
    ALOAD 21
    ALOAD 17
    ALOAD 18
    ALOAD 2
    LLOAD 9
    INVOKESTATIC com/huangder/lumibooks/util/parser/TxtParser.forEachLinePrefix$lambda$17$emit$16 (Lkotlin/jvm/functions/Function3;Lkotlin/jvm/internal/Ref$LongRef;[BLkotlin/jvm/internal/Ref$IntRef;Lcom/huangder/lumibooks/util/parser/TxtParser$EncodingInfo;J)V
   L65
    LINENUMBER 586 L65
    GOTO L66
   L66
    GETSTATIC kotlin/Unit.INSTANCE : Lkotlin/Unit;
   L67
    LINENUMBER 535 L67
    ASTORE 14
   L1
    ICONST_1
    POP
    ALOAD 12
    ALOAD 13
    INVOKESTATIC kotlin/io/CloseableKt.closeFinally (Ljava/io/Closeable;Ljava/lang/Throwable;)V
    GOTO L68
   L68
    ALOAD 14
    GOTO L69
   L2
    ASTORE 14
    INVOKESTATIC kotlin/jvm/internal/$PseudoInsn.RESTORE_STACK_IN_TRY_CATCH ()V
    ALOAD 14
    ASTORE 13
    ALOAD 14
    ATHROW
   L3
    ASTORE 14
   L4
    ICONST_1
    POP
    ALOAD 12
    ALOAD 13
    INVOKESTATIC kotlin/io/CloseableKt.closeFinally (Ljava/io/Closeable;Ljava/lang/Throwable;)V
    GOTO L70
   L70
    ALOAD 14
    ATHROW
   L69
    POP
   L71
    LINENUMBER 587 L71
    NOP
    GOTO L16
   L16
    INVOKESTATIC kotlin/jvm/internal/InlineMarker.afterInlineCall ()V
   L72
    LINENUMBER 125 L72
    ALOAD 5
    INVOKEINTERFACE java/util/List.size ()I (itf)
    ICONST_2
    IF_ICMPLT L73
    ALOAD 5
    ARETURN
   L74
    NOP
   L73
    GOTO L7
   L8
    INVOKESTATIC kotlin/jvm/internal/InlineMarker.afterInlineCall ()V
   L75
    LINENUMBER 127 L75
    INVOKESTATIC kotlin/collections/CollectionsKt.emptyList ()Ljava/util/List;
    ARETURN
   L76
    NOP
   L77
    LOCALVARIABLE isNewline$iv Z L49 L55 28
    LOCALVARIABLE index$iv I L40 L41 27
    LOCALVARIABLE index$iv I L57 L56 27
    LOCALVARIABLE requested$iv I L35 L64 25
    LOCALVARIABLE read$iv I L36 L64 26
    LOCALVARIABLE $i$a$-use-TxtParser$forEachLinePrefix$1$iv I L19 L66 15
    LOCALVARIABLE buffer$iv [B L21 L66 16
    LOCALVARIABLE prefix$iv [B L22 L66 17
    LOCALVARIABLE prefixLength$iv Lkotlin/jvm/internal/Ref$IntRef; L23 L66 18
    LOCALVARIABLE absolutePosition$iv J L24 L66 19
    LOCALVARIABLE lineStart$iv Lkotlin/jvm/internal/Ref$LongRef; L25 L66 21
    LOCALVARIABLE remaining$iv J L27 L66 22
    LOCALVARIABLE utf16$iv Z L31 L66 24
    LOCALVARIABLE randomAccess$iv Ljava/io/RandomAccessFile; L18 L66 14
    LOCALVARIABLE $i$f$forEachLinePrefix I L14 L16 11
    LOCALVARIABLE this_$iv Lcom/huangder/lumibooks/util/parser/TxtParser; L13 L16 6
    LOCALVARIABLE startByte$iv J L13 L16 7
    LOCALVARIABLE endByte$iv J L13 L16 9
    LOCALVARIABLE matches Ljava/util/List; L12 L73 5
    LOCALVARIABLE pattern Lkotlin/text/Regex; L9 L73 4
    LOCALVARIABLE this Lcom/huangder/lumibooks/util/parser/TxtParser; L5 L77 0
    LOCALVARIABLE file Ljava/io/File; L5 L77 1
    LOCALVARIABLE encoding Lcom/huangder/lumibooks/util/parser/TxtParser$EncodingInfo; L5 L77 2
    MAXSTACK = 8
    MAXLOCALS = 30

File is unknown
The root cause org.jetbrains.org.objectweb.asm.tree.analysis.AnalyzerException was thrown at: org.jetbrains.kotlin.codegen.optimization.common.FastAnalyzer.analyzeMainLoop(FastAnalyzer.kt:82)
	at org.jetbrains.kotlin.codegen.TransformationMethodVisitor.visitEnd(TransformationMethodVisitor.kt:89)
	at org.jetbrains.org.objectweb.asm.MethodVisitor.visitEnd(MethodVisitor.java:783)
	at org.jetbrains.org.objectweb.asm.tree.MethodNode.accept(MethodNode.java:772)
	at org.jetbrains.kotlin.backend.jvm.codegen.ClassCodegen.generateMethod(ClassCodegen.kt:453)
	at org.jetbrains.kotlin.backend.jvm.codegen.ClassCodegen.generate(ClassCodegen.kt:168)
	at org.jetbrains.kotlin.backend.jvm.FileCodegen.lower(JvmPhases.kt:39)
	at org.jetbrains.kotlin.backend.common.phaser.PhaseFactoriesKt.createFilePhase$lambda$4(PhaseFactories.kt:71)
	at org.jetbrains.kotlin.backend.common.phaser.PhaseBuildersKt$createSimpleNamedCompilerPhase$1.phaseBody(PhaseBuilders.kt:69)
	at org.jetbrains.kotlin.backend.common.phaser.SimpleNamedCompilerPhase.phaseBody(CompilerPhase.kt:226)
	at org.jetbrains.kotlin.backend.common.phaser.AbstractNamedCompilerPhase.invoke(CompilerPhase.kt:113)
	at org.jetbrains.kotlin.backend.common.phaser.PerformByIrFilePhase.invokeSequential(performByIrFile.kt:62)
	at org.jetbrains.kotlin.backend.common.phaser.PerformByIrFilePhase.invoke(performByIrFile.kt:52)
	at org.jetbrains.kotlin.backend.common.phaser.PerformByIrFilePhase.invoke(performByIrFile.kt:38)
	at org.jetbrains.kotlin.backend.common.phaser.NamedCompilerPhase.phaseBody(CompilerPhase.kt:166)
	at org.jetbrains.kotlin.backend.common.phaser.AbstractNamedCompilerPhase.invoke(CompilerPhase.kt:113)
	at org.jetbrains.kotlin.backend.common.phaser.CompositePhase.invoke(PhaseBuilders.kt:27)
	at org.jetbrains.kotlin.backend.common.phaser.CompositePhase.invoke(PhaseBuilders.kt:14)
	at org.jetbrains.kotlin.backend.common.phaser.NamedCompilerPhase.phaseBody(CompilerPhase.kt:166)
	at org.jetbrains.kotlin.backend.common.phaser.AbstractNamedCompilerPhase.invoke(CompilerPhase.kt:113)
	at org.jetbrains.kotlin.backend.common.phaser.CompilerPhaseKt.invokeToplevel(CompilerPhase.kt:62)
	at org.jetbrains.kotlin.backend.jvm.JvmIrCodegenFactory.invokeCodegen(JvmIrCodegenFactory.kt:371)
	at org.jetbrains.kotlin.codegen.CodegenFactory.generateModule(CodegenFactory.kt:47)
	at org.jetbrains.kotlin.backend.jvm.JvmIrCodegenFactory.generateModuleInFrontendIRMode(JvmIrCodegenFactory.kt:433)
	at org.jetbrains.kotlin.cli.jvm.compiler.pipeline.JvmCompilerPipelineKt.generateCodeFromIr(jvmCompilerPipeline.kt:246)
	at org.jetbrains.kotlin.cli.jvm.compiler.pipeline.JvmCompilerPipelineKt.compileModulesUsingFrontendIrAndLightTree(jvmCompilerPipeline.kt:142)
	at org.jetbrains.kotlin.cli.jvm.K2JVMCompiler.doExecute(K2JVMCompiler.kt:148)
	at org.jetbrains.kotlin.cli.jvm.K2JVMCompiler.doExecute(K2JVMCompiler.kt:43)
	at org.jetbrains.kotlin.cli.common.CLICompiler.execImpl(CLICompiler.kt:103)
	at org.jetbrains.kotlin.cli.common.CLICompiler.execImpl(CLICompiler.kt:49)
	at org.jetbrains.kotlin.cli.common.CLITool.exec(CLITool.kt:101)
	at org.jetbrains.kotlin.incremental.IncrementalJvmCompilerRunner.runCompiler(IncrementalJvmCompilerRunner.kt:464)
	at org.jetbrains.kotlin.incremental.IncrementalJvmCompilerRunner.runCompiler(IncrementalJvmCompilerRunner.kt:73)
	at org.jetbrains.kotlin.incremental.IncrementalCompilerRunner.doCompile(IncrementalCompilerRunner.kt:506)
	at org.jetbrains.kotlin.incremental.IncrementalCompilerRunner.compileImpl(IncrementalCompilerRunner.kt:423)
	at org.jetbrains.kotlin.incremental.IncrementalCompilerRunner.tryCompileIncrementally$lambda$9$compile(IncrementalCompilerRunner.kt:249)
	at org.jetbrains.kotlin.incremental.IncrementalCompilerRunner.tryCompileIncrementally(IncrementalCompilerRunner.kt:267)
	at org.jetbrains.kotlin.incremental.IncrementalCompilerRunner.compile(IncrementalCompilerRunner.kt:120)
	at org.jetbrains.kotlin.daemon.CompileServiceImplBase.execIncrementalCompiler(CompileServiceImpl.kt:675)
	at org.jetbrains.kotlin.daemon.CompileServiceImplBase.access$execIncrementalCompiler(CompileServiceImpl.kt:92)
	at org.jetbrains.kotlin.daemon.CompileServiceImpl.compile(CompileServiceImpl.kt:1660)
	at java.base/jdk.internal.reflect.DirectMethodHandleAccessor.invoke(Unknown Source)
	at java.base/java.lang.reflect.Method.invoke(Unknown Source)
	at java.rmi/sun.rmi.server.UnicastServerRef.dispatch(Unknown Source)
	at java.rmi/sun.rmi.transport.Transport$1.run(Unknown Source)
	at java.rmi/sun.rmi.transport.Transport$1.run(Unknown Source)
	at java.base/java.security.AccessController.doPrivileged(Unknown Source)
	at java.rmi/sun.rmi.transport.Transport.serviceCall(Unknown Source)
	at java.rmi/sun.rmi.transport.tcp.TCPTransport.handleMessages(Unknown Source)
	at java.rmi/sun.rmi.transport.tcp.TCPTransport$ConnectionHandler.run0(Unknown Source)
	at java.rmi/sun.rmi.transport.tcp.TCPTransport$ConnectionHandler.lambda$run$0(Unknown Source)
	at java.base/java.security.AccessController.doPrivileged(Unknown Source)
	at java.rmi/sun.rmi.transport.tcp.TCPTransport$ConnectionHandler.run(Unknown Source)
	at java.base/java.util.concurrent.ThreadPoolExecutor.runWorker(Unknown Source)
	at java.base/java.util.concurrent.ThreadPoolExecutor$Worker.run(Unknown Source)
	at java.base/java.lang.Thread.run(Unknown Source)
Caused by: org.jetbrains.org.objectweb.asm.tree.analysis.AnalyzerException: Error at instruction #387 INVOKESTATIC com/huangder/lumibooks/util/parser/TxtParser.forEachLinePrefix$lambda$17$emit$16 (Lkotlin/jvm/functions/Function3;Lkotlin/jvm/internal/Ref$LongRef;[BLkotlin/jvm/internal/Ref$IntRef;Lcom/huangder/lumibooks/util/parser/TxtParser$EncodingInfo;J)V: Cannot pop operand off an empty stack.
current: {
  locals: [
    #0: OBJECT
    #1: OBJECT
    #2: OBJECT
    #3: OBJECT
    #4: OBJECT
    #5: OBJECT
    #6: OBJECT
    #7: LONG
    #8: UNINITIALIZED
    #9: LONG
    #10: UNINITIALIZED
    #11: INT
    #12: OBJECT
    #13: OBJECT
    #14: OBJECT
    #15: INT
    #16: OBJECT
    #17: OBJECT
    #18: OBJECT
    #19: LONG
    #20: UNINITIALIZED
    #21: OBJECT
    #22: LONG
    #23: UNINITIALIZED
    #24: INT
    #25: UNINITIALIZED
    #26: UNINITIALIZED
    #27: UNINITIALIZED
    #28: UNINITIALIZED
    #29: UNINITIALIZED
  ]
  stack: size=0 []
}

	at org.jetbrains.kotlin.codegen.optimization.common.FastAnalyzer.analyzeMainLoop(FastAnalyzer.kt:82)
	at org.jetbrains.kotlin.codegen.optimization.common.FastAnalyzer.analyze(FastAnalyzer.kt:53)
	at org.jetbrains.kotlin.codegen.optimization.fixStack.FixStackAnalyzer.analyze(FixStackAnalyzer.kt:60)
	at org.jetbrains.kotlin.codegen.optimization.fixStack.FixStackMethodTransformer.analyzeAndTransformBreakContinueGotos(FixStackMethodTransformer.kt:55)
	at org.jetbrains.kotlin.codegen.optimization.fixStack.FixStackMethodTransformer.transform(FixStackMethodTransformer.kt:44)
	at org.jetbrains.kotlin.codegen.optimization.transformer.CompositeMethodTransformer.transform(CompositeMethodTransformer.kt:25)
	at org.jetbrains.kotlin.codegen.optimization.transformer.CompositeMethodTransformer.transform(CompositeMethodTransformer.kt:25)
	at org.jetbrains.kotlin.codegen.optimization.OptimizationMethodVisitor.performTransformations(OptimizationMethodVisitor.kt:70)
	at org.jetbrains.kotlin.codegen.TransformationMethodVisitor.visitEnd(TransformationMethodVisitor.kt:67)
	... 54 more
Caused by: java.lang.IndexOutOfBoundsException: Cannot pop operand off an empty stack.
	at org.jetbrains.org.objectweb.asm.tree.analysis.Frame.pop(Frame.java:228)
	at org.jetbrains.kotlin.codegen.optimization.fixStack.FixStackAnalyzer$FixStackFrame.pop(FixStackAnalyzer.kt:157)
	at org.jetbrains.kotlin.codegen.optimization.fixStack.FixStackAnalyzer$FixStackFrame.pop(FixStackAnalyzer.kt:98)
	at org.jetbrains.org.objectweb.asm.tree.analysis.Frame.executeInvokeInsn(Frame.java:640)
	at org.jetbrains.org.objectweb.asm.tree.analysis.Frame.execute(Frame.java:573)
	at org.jetbrains.kotlin.codegen.optimization.fixStack.FixStackAnalyzer$FixStackFrame.execute(FixStackAnalyzer.kt:126)
	at org.jetbrains.kotlin.codegen.optimization.common.FastAnalyzer.analyzeInstruction(FastAnalyzer.kt:111)
	at org.jetbrains.kotlin.codegen.optimization.common.FastAnalyzer.analyzeMainLoop(FastAnalyzer.kt:74)
	... 62 more


